{"indexes":[{"v":{"$numberInt":"2"},"key":{"_id":{"$numberInt":"1"}},"name":"_id_"},{"v":{"$numberInt":"2"},"key":{"state":{"$numberInt":"1"}},"name":"state_1","background":true},{"v":{"$numberInt":"2"},"key":{"act":{"$numberInt":"1"}},"name":"act_1","background":true},{"v":{"$numberInt":"2"},"key":{"rule":{"$numberInt":"1"}},"name":"rule_1","background":true},{"v":{"$numberInt":"2"},"key":{"category":{"$numberInt":"1"}},"name":"category_1","background":true},{"v":{"$numberInt":"2"},"key":{"status":{"$numberInt":"1"}},"name":"status_1","background":true},{"v":{"$numberInt":"2"},"key":{"description":{"$numberInt":"1"}},"name":"description_1","background":true},{"v":{"$numberInt":"2"},"key":{"image":{"$numberInt":"1"}},"name":"image_1","background":true},{"v":{"$numberInt":"2"},"key":{"document":{"$numberInt":"1"}},"name":"document_1","background":true},{"v":{"$numberInt":"2"},"key":{"approvedate":{"$numberInt":"1"}},"name":"approvedate_1","background":true},{"v":{"$numberInt":"2"},"key":{"risk":{"$numberInt":"1"}},"name":"risk_1","background":true},{"v":{"$numberInt":"2"},"key":{"created_at":{"$numberInt":"1"}},"name":"created_at_1","background":true},{"v":{"$numberInt":"2"},"key":{"date":{"$numberInt":"1"}},"name":"date_1","background":true},{"v":{"$numberInt":"2"},"key":{"compliances":{"$numberInt":"1"}},"name":"compliances_1","background":true},{"v":{"$numberInt":"2"},"key":{"documents":{"$numberInt":"1"}},"name":"documents_1","background":true},{"v":{"$numberInt":"2"},"key":{"form":{"$numberInt":"1"}},"name":"form_1","background":true},{"v":{"$numberInt":"2"},"key":{"quotation":{"$numberInt":"1"}},"name":"quotation_1","background":true},{"v":{"$numberInt":"2"},"key":{"question":{"$numberInt":"1"}},"name":"question_1","background":true},{"v":{"$numberInt":"2"},"key":{"updated_at":{"$numberInt":"1"}},"name":"updated_at_1","background":true},{"v":{"$numberInt":"2"},"key":{"frequency":{"$numberInt":"1"}},"name":"frequency_1","background":true},{"v":{"$numberInt":"2"},"key":{"rejected_at":{"$numberInt":"1"}},"name":"rejected_at_1","background":true},{"v":{"$numberInt":"2"},"key":{"reason":{"$numberInt":"1"}},"name":"reason_1","background":true},{"v":{"$numberInt":"2"},"key":{"branchname":{"$numberInt":"1"}},"name":"branchname_1","background":true}],"uuid":"6a18bbe7a7e74009bfbdcdf582c68c22","collectionName":"checklists","type":"collection"}